ax_env/__init__.py
extra_requirements/requirements-tests.txt
ax_env-0.3.3.dist-info/METADATA
ax_env-0.3.3.dist-info/WHEEL
ax_env-0.3.3.dist-info/top_level.txt
ax_env-0.3.3.dist-info/RECORD
