Metadata-Version: 2.1
Name: ax-env
Version: 0.3.3
Summary: dependency manager for XENONnT package
Home-page: https://github.com/XENONnT/ax_env
Author: J. R. Angevaare
License: UNKNOWN
Platform: UNKNOWN
Classifier: Development Status :: 5 - Production/Stable
Classifier: License :: OSI Approved :: BSD License
Classifier: Natural Language :: English
Classifier: Programming Language :: Python :: 3.8
Classifier: Programming Language :: Python :: 3.9
Classifier: Programming Language :: Python :: 3.10
Classifier: Intended Audience :: Science/Research
Classifier: Programming Language :: Python :: Implementation :: CPython
Classifier: Topic :: Scientific/Engineering :: Physics
Requires-Python: >=3.8
Requires-Dist: awkward (==1.10.1)
Requires-Dist: blosc (==1.11.1)
Requires-Dist: bokeh (==2.4.3)
Requires-Dist: boltons (==21.0.0)
Requires-Dist: commentjson (==0.9.0)
Requires-Dist: coverage (==6.5.0)
Requires-Dist: coveralls (==3.3.1)
Requires-Dist: dask (==2023.2.0)
Requires-Dist: dask-jobqueue (==0.8.1)
Requires-Dist: datashader (==0.14.4)
Requires-Dist: dill (==0.3.5.1)
Requires-Dist: distributed
Requires-Dist: flake8 (==6.0.0)
Requires-Dist: fsspec (==2022.11.0)
Requires-Dist: gitpython (==3.1.30)
Requires-Dist: holoviews (==1.15.4)
Requires-Dist: hypothesis (==6.46.2)
Requires-Dist: immutabledict (==2.2.3)
Requires-Dist: ipywidgets (==8.0.4)
Requires-Dist: jinja2 (==3.1.2)
Requires-Dist: jupyter-client (==8.0.3)
Requires-Dist: keras (==2.11.0)
Requires-Dist: lz4 (==4.3.2)
Requires-Dist: matplotlib (==3.5.3)
Requires-Dist: memory-profiler (==0.61.0)
Requires-Dist: mongomock (==4.1.2)
Requires-Dist: multihist (==0.6.5)
Requires-Dist: nbmake (==1.4.1)
Requires-Dist: nestpy (==2.0.0)
Requires-Dist: npshmex (==0.2.1)
Requires-Dist: numba (==0.56.4)
Requires-Dist: numexpr (==2.8.4)
Requires-Dist: packaging (==23.0)
Requires-Dist: pandas (==1.5.3)
Requires-Dist: panel (==0.14.3)
Requires-Dist: pdmongo (==0.3.4)
Requires-Dist: psutil (==5.9.4)
Requires-Dist: pymongo (==3.13.0)
Requires-Dist: pytest (==7.2.1)
Requires-Dist: pytest-cov (==4.0.0)
Requires-Dist: pytest-xdist (==3.2.0)
Requires-Dist: rframe (==0.2.6)
Requires-Dist: scikit-learn (==1.2.1)
Requires-Dist: scipy (==1.10.0)
Requires-Dist: tensorflow (==2.11.0)
Requires-Dist: typing-extensions (==4.5.0)
Requires-Dist: tqdm (==4.64.1)
Requires-Dist: uproot (==4.3.7)
Requires-Dist: utilix (==0.7.2)
Requires-Dist: xarray (==2022.12.0)
Requires-Dist: xedocs (==0.2.14)
Requires-Dist: zarr (==2.14.1)
Requires-Dist: zstd (==1.5.4.0)
